pyspla/__init__.py
pyspla/__main__.py
pyspla/bridge.py
pyspla/library.py
pyspla/libspla_arm64.dylib
pyspla/libspla_x64.dylib
pyspla/libspla_x64.so
pyspla/matrix.py
pyspla/op.py
pyspla/schedule.py
pyspla/spla_x64.dll
pyspla/type.py
pyspla/vector.py
pyspla/version.py
pyspla-0.0.5.dist-info/LICENSE.md
pyspla-0.0.5.dist-info/METADATA
pyspla-0.0.5.dist-info/WHEEL
pyspla-0.0.5.dist-info/top_level.txt
pyspla-0.0.5.dist-info/RECORD
