Metadata-Version: 2.1
Name: pyspla
Version: 0.0.5
Summary: spla library python bindings
Home-page: https://github.com/JetBrains-Research/spla
Author: Egor Orachev
Author-email: egororachyov@gmail.com
License: MIT
Project-URL: Spla project, https://github.com/JetBrains-Research/spla
Project-URL: Bug Tracker, https://github.com/JetBrains-Research/spla/issues
Keywords: python,cplusplus,generalized,sparse-matrix,linear-algebra,graph-analysis,graph-algorithms,graphblas,nvidia-cuda,opencl,gpu
Platform: UNKNOWN
Classifier: Development Status :: 1 - Planning
Classifier: Programming Language :: Python :: 3
Classifier: Programming Language :: C++
Classifier: License :: OSI Approved :: MIT License
Classifier: Operating System :: Microsoft :: Windows
Classifier: Operating System :: POSIX :: Linux
Classifier: Operating System :: MacOS
Classifier: Environment :: GPU
Classifier: Environment :: Console
Classifier: Intended Audience :: Developers
Classifier: Intended Audience :: End Users/Desktop
Classifier: Intended Audience :: Information Technology
Classifier: Intended Audience :: Science/Research
Classifier: Natural Language :: English
Classifier: Topic :: Scientific/Engineering
Classifier: Topic :: Scientific/Engineering :: Mathematics
Classifier: Topic :: Scientific/Engineering :: Information Analysis
Classifier: Topic :: Scientific/Engineering :: Bio-Informatics
Requires-Python: >=3.0
